cybernetickit/__init__.py
cybernetickit/arxiv.py
cybernetickit/block.py
cybernetickit/city.py
cybernetickit/constants.py
cybernetickit/county.py
cybernetickit/district.py
cybernetickit/experimental/__init__.py
cybernetickit/experimental/theoryofchange.py
cybernetickit/geo.py
cybernetickit/interfaces.py
cybernetickit/library.py
cybernetickit/opendata.py
cybernetickit/oppression.py
cybernetickit/osf.py
cybernetickit/sensor.py
cybernetickit/state.py
cybernetickit/stix.py
cybernetickit/tract.py
cybernetickit/transforms.py
cybernetickit/util.py
cybernetickit/vega.py
cybernetickit/web.py
cybernetickit-0.3.2b4.dist-info/COPYING.LESSER
cybernetickit-0.3.2b4.dist-info/LICENSE
cybernetickit-0.3.2b4.dist-info/WHEEL
cybernetickit-0.3.2b4.dist-info/METADATA
cybernetickit-0.3.2b4.dist-info/RECORD
