Metadata-Version: 2.1
Name: cybernetickit
Version: 0.3.2b4
Summary: The Cybernetic Kit is a set of conventions and techniques useful for making software-driven social impact.
License: LGPL-3.0-or-later
Author: Jurnell Cockhren
Author-email: jurnell@civichacker.com
Requires-Python: >=3.7,<4.0
Classifier: Development Status :: 3 - Alpha
Classifier: License :: OSI Approved :: GNU Lesser General Public License v3 or later (LGPLv3+)
Classifier: Programming Language :: Python :: 3
Classifier: Programming Language :: Python :: 3.10
Classifier: Programming Language :: Python :: 3.7
Classifier: Programming Language :: Python :: 3.8
Classifier: Programming Language :: Python :: 3.9
Classifier: Topic :: Internet :: WWW/HTTP :: Indexing/Search
Classifier: Topic :: Scientific/Engineering
Classifier: Topic :: Software Development :: Libraries :: Python Modules
Requires-Dist: elasticsearch-dsl (>=7.0.0,<8.0.0)
Requires-Dist: typing-inspect (>=0.7.1,<0.8.0); python_version >= "3.7" and python_version < "3.8"
